{
    "blacklist_info": [
        "Merchant22",
        "Merchant22",
        "Merchant23",
        "Merchant28",
        "Merchant21",
        "Merchant28",
        "Merchant29",
        "Merchant22",
        "Merchant27",
        "Merchant30"
    ],
    "credit_scores": {
        "C000": 826,
        "C001": 572,
        "C002": 706,
        "C003": 437,
        "C004": 724,
        "C005": 771,
        "C006": 358,
        "C007": 823,
        "C008": 830,
        "C009": 684,
        "C010": 504,
        "C011": 327,
        "C012": 789,
        "C013": 444,
        "C014": 705,
        "C015": 687,
        "C016": 376,
        "C017": 795,
        "C018": 720,
        "C019": 504,
        "C020": 811,
        "C021": 767,
        "C022": 327,
        "C023": 656,
        "C024": 317,
        "C025": 668,
        "C026": 684,
        "C027": 534,
        "C028": 625,
        "C029": 625,
        "C030": 799,
        "C031": 636,
        "C032": 503,
        "C033": 596,
        "C034": 514,
        "C035": 643,
        "C036": 407,
        "C037": 553,
        "C038": 730,
        "C039": 704,
        "C040": 624,
        "C041": 474,
        "C042": 836,
        "C043": 664,
        "C044": 805,
        "C045": 338,
        "C046": 456,
        "C047": 392,
        "C048": 837,
        "C049": 756,
        "C050": 767,
        "C051": 551,
        "C052": 693,
        "C053": 798,
        "C054": 775,
        "C055": 502,
        "C056": 760,
        "C057": 503,
        "C058": 719,
        "C059": 304,
        "C060": 643,
        "C061": 470,
        "C062": 456,
        "C063": 670,
        "C064": 464,
        "C065": 633,
        "C066": 370,
        "C067": 506,
        "C068": 637,
        "C069": 373,
        "C070": 654,
        "C071": 474,
        "C072": 583,
        "C073": 395,
        "C074": 667,
        "C075": 722,
        "C076": 778,
        "C077": 680,
        "C078": 534,
        "C079": 811,
        "C080": 556,
        "C081": 621,
        "C082": 722,
        "C083": 435,
        "C084": 489,
        "C085": 334,
        "C086": 677,
        "C087": 773,
        "C088": 324,
        "C089": 476,
        "C090": 536,
        "C091": 765,
        "C092": 411,
        "C093": 552,
        "C094": 511,
        "C095": 387,
        "C096": 615,
        "C097": 711,
        "C098": 448,
        "C099": 321
    },
    "fraud_reports": {
        "C000": 4,
        "C001": 1,
        "C002": 0,
        "C003": 3,
        "C004": 1,
        "C005": 0,
        "C006": 4,
        "C007": 0,
        "C008": 1,
        "C009": 0,
        "C010": 0,
        "C011": 2,
        "C012": 2,
        "C013": 0,
        "C014": 4,
        "C015": 4,
        "C016": 3,
        "C017": 4,
        "C018": 2,
        "C019": 0,
        "C020": 2,
        "C021": 4,
        "C022": 0,
        "C023": 5,
        "C024": 5,
        "C025": 0,
        "C026": 5,
        "C027": 3,
        "C028": 5,
        "C029": 3,
        "C030": 0,
        "C031": 5,
        "C032": 1,
        "C033": 2,
        "C034": 3,
        "C035": 3,
        "C036": 5,
        "C037": 4,
        "C038": 4,
        "C039": 1,
        "C040": 5,
        "C041": 4,
        "C042": 3,
        "C043": 3,
        "C044": 3,
        "C045": 5,
        "C046": 3,
        "C047": 3,
        "C048": 3,
        "C049": 1,
        "C050": 3,
        "C051": 5,
        "C052": 1,
        "C053": 4,
        "C054": 1,
        "C055": 2,
        "C056": 0,
        "C057": 5,
        "C058": 2,
        "C059": 1,
        "C060": 0,
        "C061": 4,
        "C062": 4,
        "C063": 0,
        "C064": 3,
        "C065": 0,
        "C066": 0,
        "C067": 4,
        "C068": 5,
        "C069": 3,
        "C070": 3,
        "C071": 5,
        "C072": 0,
        "C073": 5,
        "C074": 5,
        "C075": 1,
        "C076": 3,
        "C077": 1,
        "C078": 0,
        "C079": 3,
        "C080": 5,
        "C081": 1,
        "C082": 3,
        "C083": 5,
        "C084": 0,
        "C085": 4,
        "C086": 3,
        "C087": 3,
        "C088": 3,
        "C089": 2,
        "C090": 2,
        "C091": 1,
        "C092": 3,
        "C093": 1,
        "C094": 3,
        "C095": 0,
        "C096": 0,
        "C097": 0,
        "C098": 5,
        "C099": 4
    }
}